matebot/__init__.py
matebot/base.py
matebot/dash.py
matebot/fn.py
matebot/val.py
matebot/websocket.py
matebot/dashboard/__init__.py
matebot/dashboard/automations.py
matebot/dashboard/base.py
matebot/dashboard/builtin.py
matebot/dashboard/defender.py
matebot/dashboard/giveaway.py
matebot/dashboard/guild.py
matebot/dashboard/levels.py
matebot/dashboard/moderation.py
matebot/dashboard/slash.py
matebot/dashboard/tempchannels.py
matebot/dashboard/welcome.py
matebot/dashboard/types/__init__.py
matebot/dashboard/types/action.py
matebot/dashboard/types/actionrow.py
matebot/dashboard/types/embed.py
matebot/dashboard/types/guild.py
matebot/dashboard/types/image.py
matebot/dashboard/types/permission.py
matebot/fortnite/__init__.py
matebot/fortnite/banners.py
matebot/fortnite/base.py
matebot/fortnite/cosmetics.py
matebot/fortnite/items.py
matebot/fortnite/newdisplayassets.py
matebot/fortnite/quests.py
matebot/fortnite/shop.py
matebot/fortnite/tracks.py
matebot/valorant/__init__.py
matebot/valorant/base.py
matebot/valorant/buddy.py
matebot/valorant/bundle.py
matebot/valorant/character.py
matebot/valorant/map.py
matebot/valorant/playercard.py
matebot/valorant/spray.py
matebot/valorant/weapon.py
matebot/valorant/ws.py
matebotpy-1.1.7.dist-info/LICENSE
matebotpy-1.1.7.dist-info/METADATA
matebotpy-1.1.7.dist-info/WHEEL
matebotpy-1.1.7.dist-info/top_level.txt
matebotpy-1.1.7.dist-info/RECORD
